setup.py
com/__init__.py
com/matttproud/__init__.py
com/matttproud/quantile/__init__.py
quantile.egg-info/PKG-INFO
quantile.egg-info/SOURCES.txt
quantile.egg-info/dependency_links.txt
quantile.egg-info/top_level.txt