Metadata-Version: 1.1
Name: quantile
Version: 0.0.1
Summary: Python Implementation of Graham Cormode and S. Muthukrishnan's Effective Computation of Biased Quantiles over Data Streams in ICDE'05
Home-page: https://github.com/matttproud/python_quantile_estimation
Author: Matt T. Proud
Author-email: matt.proud@gmail.com
License: Apache License 2.0
Platform: Platform Independent
Classifier: Development Status :: 3 - Alpha
Classifier: Intended Audience :: Developers
Classifier: License :: OSI Approved :: Apache Software License
Classifier: Operating System :: OS Independent
Classifier: Topic :: Scientific/Engineering :: Mathematics
